statick_tool/plugins/discovery/css.py
statick_tool/plugins/discovery/html.py
statick_tool/plugins/discovery/javascript.py
statick_tool/plugins/tool/eslint.py
statick_tool/plugins/tool/htmllint.py
statick_tool/plugins/tool/jshint.py
statick_tool/plugins/tool/stylelint.py
statick_tool/rsc/.htmllintrc
statick_tool/rsc/.jshintrc
statick_tool/rsc/.stylelintrc
statick_tool/rsc/eslint-profile.yaml
statick_tool/rsc/eslint.config.mjs
statick_tool/rsc/htmllint-profile.yaml
statick_tool/rsc/jshint-profile.yaml
statick_tool/rsc/stylelint-profile.yaml
statick_tool/rsc/web-config.yaml
statick_tool/rsc/web-profile.yaml
statick_web-0.3.0.dist-info/LICENSE
statick_web-0.3.0.dist-info/METADATA
statick_web-0.3.0.dist-info/WHEEL
statick_web-0.3.0.dist-info/entry_points.txt
statick_web-0.3.0.dist-info/top_level.txt
statick_web-0.3.0.dist-info/RECORD
