Metadata-Version: 2.2
Name: statick-web
Version: 0.3.0
Summary: Statick analysis plugins for Web (css, html, js) files.
Author: NIWC Pacific
License: CC0-1.0
Project-URL: Homepage, https://github.com/sscpac/statick-web
Project-URL: Bug Tracker, https://github.com/sscpac/statick-web/issues
Classifier: License :: CC0 1.0 Universal (CC0 1.0) Public Domain Dedication
Classifier: Programming Language :: Python :: 3
Classifier: Programming Language :: Python :: 3.9
Classifier: Programming Language :: Python :: 3.10
Classifier: Programming Language :: Python :: 3.11
Classifier: Programming Language :: Python :: 3.12
Classifier: Programming Language :: Python :: 3.13
Classifier: Topic :: Software Development :: Quality Assurance
Classifier: Topic :: Software Development :: Testing
Classifier: Typing :: Typed
Requires-Python: >=3.9
License-File: LICENSE
Requires-Dist: importlib_metadata
Requires-Dist: statick
Provides-Extra: test
Requires-Dist: coverage; extra == "test"
Requires-Dist: mock; extra == "test"
Requires-Dist: pytest; extra == "test"
Requires-Dist: pytest-cov; extra == "test"
Requires-Dist: statick-md; extra == "test"
Requires-Dist: tox; extra == "test"
Requires-Dist: tox-gh-actions; extra == "test"
Provides-Extra: docs
Requires-Dist: yaml-1.3; extra == "docs"
